ipware/__init__.py
ipware/__version__.py
ipware/apps.py
ipware/ip.py
django_ipware-7.0.0.dist-info/LICENSE
django_ipware-7.0.0.dist-info/METADATA
django_ipware-7.0.0.dist-info/WHEEL
django_ipware-7.0.0.dist-info/top_level.txt
django_ipware-7.0.0.dist-info/RECORD
